Workbook
Name aporte: Simulador_Financeiro!$D$17:$D$17
Name patrimonio: Simulador_Financeiro!$D$20:$D$20
Name perfil_investidor: Simulador_Financeiro!$D$32:$D$32
Name qtd_anos: Simulador_Financeiro!$D$18:$D$18
Name rendimento_carteira: Simulador_Financeiro!$D$13:$D$13
Name salario: Simulador_Financeiro!$D$12:$D$12
Name sugestao_investimento: Simulador_Financeiro!$D$14:$D$14
Name taxa_mensal: Simulador_Financeiro!$D$19:$D$19

Sheet Simulador_Financeiro
B11: Configurações
B12: Salário | D12: 4200
B13: Rendimento Carteira | D13: 0.006
B14: Sugestão de investimento | D14: =D12*30% -> 1260
B16: Investimento Mensal
B17: Valor do investimento mensal | D17: 1260
B18: Período de investimento em anos | D18: 10
B19: Taxa de rendimento mensal | D19: 0.01079
B20: Patrimônio acumulado | D20: {=FV(taxa_mensal,qtd_anos*12,aporte*-1)} -> 306538.11
B21: Dividendos mensais | D21: {=patrimonio*rendimento_carteira} -> 1839.2286
B23: Projeção de Cenários | C23: Patrimônio | D23: Dividendo
A24: 2 | B24: Em 2 anos | C24: =FV($D$19,$A24*12,$D$17*-1) -> 34306.81 | D24: {=C24*rendimento_carteira} -> 205.84086
A25: 5 | B25: Em 5 anos | C25: =FV($D$19,$A25*12,$D$17*-1) -> 105558.91 | D25: {=C25*rendimento_carteira} -> 633.35347
A26: 10 | B26: Em 10 anos | C26: =FV($D$19,$A26*12,$D$17*-1) -> 306538.11 | D26: {=C26*rendimento_carteira} -> 1839.2286
A27: 20 | B27: Em 20 anos | C27: =FV($D$19,$A27*12,$D$17*-1) -> 1417750 | D27: {=C27*rendimento_carteira} -> 8506.4999
A28: 30 | B28: Em 30 anos | C28: =FV($D$19,$A28*12,$D$17*-1) -> 5445933.8 | D28: {=C28*rendimento_carteira} -> 32675.603
B32: PERFIL | D32: Conservador
B33: VALOR DO INVESTIMENTO MENSAL | D33: {=aporte} -> 1260
B35: TIPO DE FII | C35: PERCENTUAL SUGERIDO | D35: VALORES
B36: PAPEL | C36: {=VLOOKUP(perfil_investidor&" - "&B36,Perfil_Investidores!$A:$D,4,FALSE)} -> 0.3 | D36: =C36*$D$33 -> 378
B37: TIJOLO | C37: {=VLOOKUP(perfil_investidor&" - "&B37,Perfil_Investidores!$A:$D,4,FALSE)} -> 0.5 | D37: =C37*$D$33 -> 630
B38: HÍBRIDOS | C38: {=VLOOKUP(perfil_investidor&" - "&B38,Perfil_Investidores!$A:$D,4,FALSE)} -> 0.1 | D38: =C38*$D$33 -> 126
B39: FOFs | C39: {=VLOOKUP(perfil_investidor&" - "&B39,Perfil_Investidores!$A:$D,4,FALSE)} -> 0.1 | D39: =C39*$D$33 -> 126
B40: DESENVOLVIMENTO | C40: {=VLOOKUP(perfil_investidor&" - "&B40,Perfil_Investidores!$A:$D,4,FALSE)} -> 0 | D40: =C40*$D$33 -> 0
B41: HOTELARIAS | C41: {=VLOOKUP(perfil_investidor&" - "&B41,Perfil_Investidores!$A:$D,4,FALSE)} -> 0 | D41: =C41*$D$33 -> 0
D42: =SUM(D36:D41) -> 1260

Sheet Perfil_Investidores
A2: CHAVE COMPOSTA | B2: PERFIL | C2: TIPO DE FII | D2: % | H2: %
A3: =$B$3&" - "&C3 -> Conservador - PAPEL | B3: Conservador | C3: PAPEL | D3: 0.3 | G3: Moderado - TIJOLO | H3: =VLOOKUP(G3,$A:$D,4,FALSE) -> 0.35
A4: =$B$3&" - "&C4 -> Conservador - TIJOLO | B4: Conservador | C4: TIJOLO | D4: 0.5
A5: =$B$3&" - "&C5 -> Conservador - HÍBRIDOS | B5: Conservador | C5: HÍBRIDOS | D5: 0.1
A6: =$B$3&" - "&C6 -> Conservador - FOFs | B6: Conservador | C6: FOFs | D6: 0.1
A7: =$B$3&" - "&C7 -> Conservador - DESENVOLVIMENTO | B7: Conservador | C7: DESENVOLVIMENTO | D7: 0
A8: =$B$3&" - "&C8 -> Conservador - HOTELARIAS | B8: Conservador | C8: HOTELARIAS | D8: 0
A9: =$B$9&" - "&C9 -> Moderado - PAPEL | B9: Moderado | C9: PAPEL | D9: 0.32
A10: =$B$9&" - "&C10 -> Moderado - TIJOLO | B10: Moderado | C10: TIJOLO | D10: 0.35
A11: =$B$9&" - "&C11 -> Moderado - HÍBRIDOS | B11: Moderado | C11: HÍBRIDOS | D11: 0.08
A12: =$B$9&" - "&C12 -> Moderado - FOFs | B12: Moderado | C12: FOFs | D12: 0.05
A13: =$B$9&" - "&C13 -> Moderado - DESENVOLVIMENTO | B13: Moderado | C13: DESENVOLVIMENTO | D13: 0.1
A14: =$B$9&" - "&C14 -> Moderado - HOTELARIAS | B14: Moderado | C14: HOTELARIAS | D14: 0.1
A15: =$B$15&" - "&C15 -> Agressivo - PAPEL | B15: Agressivo | C15: PAPEL | D15: 0.5
A16: =$B$15&" - "&C16 -> Agressivo - TIJOLO | B16: Agressivo | C16: TIJOLO | D16: 0.1
A17: =$B$15&" - "&C17 -> Agressivo - HÍBRIDOS | B17: Agressivo | C17: HÍBRIDOS | D17: 0.05
A18: =$B$15&" - "&C18 -> Agressivo - FOFs | B18: Agressivo | C18: FOFs | D18: 0.05
A19: =$B$15&" - "&C19 -> Agressivo - DESENVOLVIMENTO | B19: Agressivo | C19: DESENVOLVIMENTO | D19: 0.2
A20: =$B$15&" - "&C20 -> Agressivo - HOTELARIAS | B20: Agressivo | C20: HOTELARIAS | D20: 0.1
